<?xml version="1.0" encoding="UTF-8"?>
<gresources>
	<gresource prefix="/kr/gooroom/greeter">
		<file preprocess="xml-stripblanks">gooroom-greeter.ui</file>
		<file preprocess="xml-stripblanks">greeter-window.ui</file>
		<file preprocess="xml-stripblanks">splash-window.ui</file>
		<file preprocess="xml-stripblanks">greeter-message-dialog.ui</file>
		<file preprocess="xml-stripblanks">greeter-password-settings-dialog.ui</file>
	</gresource>

    <gresource prefix="/kr/gooroom/greeter">
        <file compressed="true" alias="theme.css">../data/theme/theme.css</file>
    </gresource>

	<gresource prefix="/kr/gooroom/greeter">
        <file alias="arrow.svg">../data/images/arrow.svg</file>
        <file alias="logo.svg">../data/images/logo.svg</file>
	</gresource>
</gresources>
